Metadata-Version: 2.1
Name: sockA
Version: 0.0.1
Summary: SockA supported socket server!
Home-page: https://www.github.com/phucbao9x/sockA.git
License-File: LICENSE
